README.md
setup.cfg
setup.py
src/pdf_table_extract.egg-info/PKG-INFO
src/pdf_table_extract.egg-info/SOURCES.txt
src/pdf_table_extract.egg-info/dependency_links.txt
src/pdf_table_extract.egg-info/entry_points.txt
src/pdf_table_extract.egg-info/not-zip-safe
src/pdf_table_extract.egg-info/requires.txt
src/pdf_table_extract.egg-info/top_level.txt
src/pdftableextract/__init__.py
src/pdftableextract/core.py
src/pdftableextract/extracttab.py
src/pdftableextract/pnm.py
src/pdftableextract/scripts.py