Metadata-Version: 1.1
Name: pdf-table-extract
Version: 0.2
Summary: Extract Tables from PDF files
Home-page: https://github.com/codeRuth/pdf-table-extract/
Author: Ruthvik Vijayakumar
Author-email: coderuth@outlook.com
License: MIT-Expat
Download-URL: https://github.com/codeRuth/pdf-table-extract/archive/0.1.tar.gz
Keywords: PDF,tables
Platform: UNKNOWN
